nmrkit/__init__.py
nmrkit/core/__init__.py
nmrkit/core/data.py
nmrkit/io/__init__.py
nmrkit/io/base.py
nmrkit/io/formats/__init__.py
nmrkit/io/formats/delta.py
nmrkit/io/formats/topspin.py
nmrkit/processing/__init__.py
nmrkit/processing/complex.py
nmrkit/processing/ft.py
nmrkit/processing/phase.py
nmrkit/processing/resize.py
nmrkit/processing/window.py
nmrkit/processing/workflows/__init__.py
nmrkit/processing/workflows/basic_1d.py
nmrkit/processing/workflows/basic_2d.py
nmrkit/utils/__init__.py
nmrkit/utils/complex.py
nmrkit/utils/validation.py
nmrkit/visualization/__init__.py
nmrkit/visualization/plotting.py
nmrkit-0.1.0.dist-info/METADATA
nmrkit-0.1.0.dist-info/WHEEL
nmrkit-0.1.0.dist-info/licenses/LICENSE
nmrkit-0.1.0.dist-info/RECORD
