Metadata-Version: 2.4
Name: nmrkit
Version: 0.1.0
Summary: A lightweight Python library for nuclear magnetic resonance (NMR) data processing and analysis
License-File: LICENSE
Author: Jiekang Tian
Author-email: jiekangtian@gmail.com
Requires-Python: >=3.12
Classifier: Programming Language :: Python :: 3
Classifier: Programming Language :: Python :: 3.12
Classifier: Programming Language :: Python :: 3.13
Classifier: Programming Language :: Python :: 3.14
Provides-Extra: visualization
Requires-Dist: matplotlib ; extra == "visualization"
Requires-Dist: numpy
